cyberfusion/SelfDiscover/__init__.py
cyberfusion/SelfDiscover/exceptions.py
cyberfusion/SelfDiscover/main.py
cyberfusion/SelfDiscover/settings.py
cyberfusion/SelfDiscover/utilities.py
self_discover-1.0.4.dist-info/METADATA
self_discover-1.0.4.dist-info/WHEEL
self_discover-1.0.4.dist-info/top_level.txt
self_discover-1.0.4.dist-info/RECORD
