Metadata-Version: 2.1
Name: self-discover
Version: 1.0.4
Summary: self-discover serves autodiscover (Outlook) and autoconfig (Thunderbird) XML files for mail auto-configuration.
Author-email: Cyberfusion <support@cyberfusion.io>
Project-URL: Source, https://github.com/CyberfusionIO/self-discover
Requires-Dist: fastapi[all] ==0.112.0
Requires-Dist: defusedxml ==0.7.1
